freeze.py
pdm_freeze-1.0.4.dist-info/entry_points.txt
pdm_freeze-1.0.4.dist-info/WHEEL
pdm_freeze-1.0.4.dist-info/METADATA
pdm_freeze-1.0.4.dist-info/RECORD
