Metadata-Version: 2.1
Name: pdm-freeze
Version: 1.0.4
Summary: A pdm plugin is used to generate requirements.txt
Home-page: UNKNOWN
License: MIT
Author-email: Longlone <1162410187@qq.com>
Requires-Python: >=3.7
Classifier: License :: OSI Approved :: MIT License
Classifier: Programming Language :: Python :: 3
Classifier: Programming Language :: Python :: 3.7
Classifier: Programming Language :: Python :: 3.8
Classifier: Programming Language :: Python :: 3.9
